<?xml version="1.0" encoding="utf-8"?>
<openerp>
    <data noupdate="0">
    <!-- <data noupdate="1"> -->

    <!-- Solicitudes de adelanto -->
        <record id="sipreco_public_budget.adelanto_personal_permanente" model="public_budget.advance_request_type">
            <field name="name">Solicitud de Adelanto - Personal Permanente</field>
            <field name="general_return_partner_id" ref="sipreco_public_budget.personal_permanente"/>
            <field name="account_id" ref="sipreco_public_budget.account_account_19_1"/>
            <field name="return_journal_id" ref="sipreco_public_budget.miscellaneous_journal"/>
            <field name="company_id" ref="base.main_company"/>
        </record>

        <record id="sipreco_public_budget.adelanto_personal_no_permanente" model="public_budget.advance_request_type">
            <field name="name">Solicitud de Adelanto - Personal  No Permanente</field>
            <field name="general_return_partner_id" ref="sipreco_public_budget.personal_no_permanente"/>
            <field name="account_id" ref="sipreco_public_budget.account_account_19_1"/>
            <field name="return_journal_id" ref="sipreco_public_budget.miscellaneous_journal"/>
            <field name="company_id" ref="base.main_company"/>
        </record>

        <record id="sipreco_public_budget.adelanto_personal_transitorio" model="public_budget.advance_request_type">
            <field name="name">Solicitud de Adelanto - Personal  Transitorio</field>
            <field name="general_return_partner_id" ref="sipreco_public_budget.personal_transitorio"/>
            <field name="account_id" ref="sipreco_public_budget.account_account_19_1"/>
            <field name="return_journal_id" ref="sipreco_public_budget.miscellaneous_journal"/>
            <field name="company_id" ref="base.main_company"/>
        </record>

    <!-- Ordenes de pago -->
        <record id="sipreco_public_budget.orden_pago_personal_permanente" model="public_budget.advance_request_type">
            <field name="name">Orden de Pago - Personal Permanente</field>
            <field name="general_return_partner_id" ref="sipreco_public_budget.personal_permanente"/>
            <field name="account_id" ref="sipreco_public_budget.account_account_19_2"/>
            <field name="return_journal_id" ref="sipreco_public_budget.miscellaneous_journal"/>
            <field name="company_id" ref="base.main_company"/>
        </record>

        <record id="sipreco_public_budget.orden_pago_personal_no_permanente" model="public_budget.advance_request_type">
            <field name="name">Orden de Pago - Personal  No Permanente</field>
            <field name="general_return_partner_id" ref="sipreco_public_budget.personal_no_permanente"/>
            <field name="account_id" ref="sipreco_public_budget.account_account_19_2"/>
            <field name="return_journal_id" ref="sipreco_public_budget.miscellaneous_journal"/>
            <field name="company_id" ref="base.main_company"/>
        </record>

        <record id="sipreco_public_budget.orden_pago_personal_transitorio" model="public_budget.advance_request_type">
            <field name="name">Orden de Pago - Personal  Transitorio</field>
            <field name="general_return_partner_id" ref="sipreco_public_budget.personal_transitorio"/>
            <field name="account_id" ref="sipreco_public_budget.account_account_19_2"/>
            <field name="return_journal_id" ref="sipreco_public_budget.miscellaneous_journal"/>
            <field name="company_id" ref="base.main_company"/>
        </record>

    </data>
</openerp>
